{
  "barr_iters": 0,
  "is_multiobj": false,
  "max_coeff": 42.429233683366036,
  "max_obj_coeff": 1.0,
  "max_q_obj_coeff": 0.0,
  "max_qc_coeff": 0.0,
  "max_qc_lin_coeff": 0.0,
  "max_qc_rhs": 0.0,
  "max_rhs": 1.0,
  "max_var_bnd": 6.0,
  "min_coeff": 0.17218594600024706,
  "min_obj_coeff": 1.0,
  "min_q_obj_coeff": 0.0,
  "min_qc_coeff": 0.0,
  "min_qc_lin_coeff": 0.0,
  "min_qc_rhs": 0.0,
  "min_rhs": 1.0,
  "min_var_bnd": 1.0,
  "model_name": "",
  "model_sense": 1,
  "model_time": 0.7963101863861084,
  "num_bin_vars": 3623,
  "num_constr": 465,
  "num_gen_constr": 0,
  "num_int_vars": 3624,
  "num_nodes": 1,
  "num_nz": 12087,
  "num_pwl_vars": 0,
  "num_quad_coeff_nz": 0,
  "num_quad_constr": 0,
  "num_quad_nz": 0,
  "num_sos": 0,
  "num_start": 0,
  "num_vars": 3625,
  "obj_bnd": 916.0489040289052,
  "obj_const": 0.0,
  "obj_val": 916.0489040289052,
  "simplex_iters": 1242,
  "sol_count": 3,
  "status": 2,
  "mip_gap": 0.0,
  "obj_bnd_raw": 916.0489040289052,
  "pool_obj_bnd": 916.0489040289052,
  "pool_obj_val": 916.0489040289052,
  "kappa": null,
  "mip_constraints": {
    "obj": 1,
    "cover": 72,
    "flow": 375,
    "num_vehicles": 1,
    "triad_cuts": 4,
    "FA_cuts": 6,
    "AF_cuts": 6,
    "FF_cuts": 0
  },
  "log": {
    "nsh_succeed": 1,
    "nsh_fail": 0,
    "frh_succeed": 0,
    "frh_fail": 0
  },
  "network_size": {
    "generation_fragments": 1760,
    "generation_parent_paths": 418,
    "filtering_fragments_removed": 1015,
    "domination_fragments_removed": 11,
    "final_size_start_arcs": 72,
    "final_size_end_arcs": 72,
    "final_size_dp_arcs": 2673,
    "final_size_arcs": 2817,
    "final_size_fragments": 734,
    "final_size_d_nodes": 184,
    "final_size_p_nodes": 191,
    "final_size_nodes": 377
  },
  "time": {
    "data_preprocess": 0.15256905555725098,
    "network_build": 0.32808613777160645,
    "model_build": 0.06356263160705566,
    "rootcut": 0.31356215476989746,
    "rc_mip": 0.012827157974243164,
    "main_mip": 0.8387422561645508,
    "total": 1.7093493938446045
  },
  "bounds": {
    "lb_root_lp": 901.5813138961202,
    "lb_lifted_lp": 908.5983573426975,
    "ub_rc_mip": Infinity,
    "ub_final": 916.0489040289052,
    "lb_final": 916.0489040289052
  },
  "cuts": {
    "triad_cuts_lp": 4,
    "FA_cuts_lp": 6,
    "AF_cuts_lp": 6,
    "FF_cuts_lp": 0,
    "legality_main_mip": 14,
    "triad_cuts_main_mip": 4,
    "FA_cuts_main_mip": 1,
    "AF_cuts_main_mip": 1
  }
}